{
  "real_external_data_provided": false,
  "no_real_external_data_provided": true,
  "captures": [
    {
      "capture_label": "capture_0",
      "roi_source": "manifest_mask",
      "roi_pixels": 734,
      "ground_truth_available": true,
      "metric_source": "real_reference",
      "methods": [
        {
          "method_id": "fixed_alpha",
          "label": "Fixed alpha baseline",
          "metric_source": "real_reference",
          "overall_mae": 0.06213951,
          "roi_mae": 0.22364306,
          "non_roi_mae": 0.0540346,
          "temporal_error_accumulation": 0.06213951,
          "intervention_rate": 0.0
        },
        {
          "method_id": "strong_heuristic",
          "label": "Strong heuristic",
          "metric_source": "real_reference",
          "overall_mae": 0.014601393,
          "roi_mae": 0.06004584,
          "non_roi_mae": 0.012320769,
          "temporal_error_accumulation": 0.014601393,
          "intervention_rate": 0.2893398
        },
        {
          "method_id": "dsfb_host_minimum",
          "label": "DSFB host minimum",
          "metric_source": "real_reference",
          "overall_mae": 0.01795497,
          "roi_mae": 0.026542949,
          "non_roi_mae": 0.01752402,
          "temporal_error_accumulation": 0.01795497,
          "intervention_rate": 0.23019426
        }
      ]
    }
  ],
  "notes": [
    "Demo A external replay uses the same host-minimum supervisory logic as the internal suite.",
    "If no optional reference frame is supplied, ROI error becomes a lag proxy against current color and non-ROI error becomes a history-deviation proxy."
  ]
}