{
  "summary": {
    "scenario_ids": [
      "thin_reveal",
      "fast_pan",
      "diagonal_reveal",
      "reveal_band",
      "motion_bias_band",
      "layered_slats",
      "noisy_reprojection",
      "heuristic_friendly_pan",
      "contrast_pulse",
      "stability_holdout"
    ],
    "policy_ids": [
      "uniform",
      "edge_guided",
      "residual_guided",
      "contrast_guided",
      "variance_guided",
      "combined_heuristic",
      "native_trust",
      "imported_trust",
      "hybrid_trust_variance"
    ],
    "primary_behavioral_result": "On the canonical sampling scenario, imported trust reduced ROI MAE from 0.17226 for uniform allocation to 0.03184 under the same total budget.",
    "imported_trust_beats_uniform_scenarios": 8,
    "imported_trust_beats_combined_heuristic_scenarios": 8,
    "neutral_or_mixed_scenarios": [
      "contrast_pulse",
      "stability_holdout"
    ]
  },
  "scenarios": [
    {
      "scenario_id": "thin_reveal",
      "scenario_title": "Thin-Structure Reveal",
      "expectation": "BenefitExpected",
      "support_category": "PointLikeRoi",
      "sampling_taxonomy": "coverage-dominated point reveal",
      "demo_b_taxonomy": "aliasing_limited",
      "onset_frame": 6,
      "target_label": "revealed thin structure",
      "target_pixels": 1,
      "policies": [
        {
          "policy_id": "uniform",
          "label": "Uniform",
          "total_samples": 30720,
          "overall_mae": 0.0028855454,
          "overall_rmse": 0.018690385,
          "roi_mae": 0.17225969,
          "roi_rmse": 0.17225969,
          "non_roi_mae": 0.0028745178,
          "non_roi_rmse": 0.018639239,
          "roi_mean_spp": 2.0,
          "non_roi_mean_spp": 2.0,
          "max_spp": 2,
          "allocation_concentration": 1.0,
          "extra_roi_samples_vs_uniform": 0.0,
          "roi_error_reduction_per_extra_roi_sample": 0.0
        },
        {
          "policy_id": "edge_guided",
          "label": "Edge-guided",
          "total_samples": 30720,
          "overall_mae": 0.001968358,
          "overall_rmse": 0.011388795,
          "roi_mae": 0.031843167,
          "roi_rmse": 0.031843167,
          "non_roi_mae": 0.0019664129,
          "non_roi_rmse": 0.011386267,
          "roi_mean_spp": 12.0,
          "non_roi_mean_spp": 1.9993489,
          "max_spp": 12,
          "allocation_concentration": 6.001954,
          "extra_roi_samples_vs_uniform": 10.0,
          "roi_error_reduction_per_extra_roi_sample": 0.014041652
        },
        {
          "policy_id": "residual_guided",
          "label": "Residual-guided",
          "total_samples": 30720,
          "overall_mae": 0.0020736586,
          "overall_rmse": 0.012429568,
          "roi_mae": 0.031843167,
          "roi_rmse": 0.031843167,
          "non_roi_mae": 0.0020717203,
          "non_roi_rmse": 0.012427318,
          "roi_mean_spp": 12.0,
          "non_roi_mean_spp": 1.9993489,
          "max_spp": 12,
          "allocation_concentration": 6.001954,
          "extra_roi_samples_vs_uniform": 10.0,
          "roi_error_reduction_per_extra_roi_sample": 0.014041652
        },
        {
          "policy_id": "contrast_guided",
          "label": "Contrast-guided",
          "total_samples": 30720,
          "overall_mae": 0.001945844,
          "overall_rmse": 0.010726419,
          "roi_mae": 0.049770057,
          "roi_rmse": 0.049770057,
          "non_roi_mae": 0.0019427305,
          "non_roi_rmse": 0.010719249,
          "roi_mean_spp": 10.0,
          "non_roi_mean_spp": 1.9994792,
          "max_spp": 10,
          "allocation_concentration": 5.0013022,
          "extra_roi_samples_vs_uniform": 8.0,
          "roi_error_reduction_per_extra_roi_sample": 0.015311204
        },
        {
          "policy_id": "variance_guided",
          "label": "Variance-guided",
          "total_samples": 30720,
          "overall_mae": 0.0025418992,
          "overall_rmse": 0.018665897,
          "roi_mae": 0.17225969,
          "roi_rmse": 0.17225969,
          "non_roi_mae": 0.002530848,
          "non_roi_rmse": 0.018614693,
          "roi_mean_spp": 2.0,
          "non_roi_mean_spp": 2.0,
          "max_spp": 12,
          "allocation_concentration": 1.0,
          "extra_roi_samples_vs_uniform": 0.0,
          "roi_error_reduction_per_extra_roi_sample": 0.0
        },
        {
          "policy_id": "combined_heuristic",
          "label": "Combined heuristic",
          "total_samples": 30720,
          "overall_mae": 0.0018897881,
          "overall_rmse": 0.010018802,
          "roi_mae": 0.049770057,
          "roi_rmse": 0.049770057,
          "non_roi_mae": 0.001886671,
          "non_roi_rmse": 0.010011081,
          "roi_mean_spp": 10.0,
          "non_roi_mean_spp": 1.9994792,
          "max_spp": 12,
          "allocation_concentration": 5.0013022,
          "extra_roi_samples_vs_uniform": 8.0,
          "roi_error_reduction_per_extra_roi_sample": 0.015311204
        },
        {
          "policy_id": "native_trust",
          "label": "Native trust",
          "total_samples": 30720,
          "overall_mae": 0.0019218887,
          "overall_rmse": 0.010155815,
          "roi_mae": 0.17215072,
          "roi_rmse": 0.17215072,
          "non_roi_mae": 0.0019108052,
          "non_roi_rmse": 0.010060712,
          "roi_mean_spp": 7.0,
          "non_roi_mean_spp": 1.9996744,
          "max_spp": 12,
          "allocation_concentration": 3.5005698,
          "extra_roi_samples_vs_uniform": 5.0,
          "roi_error_reduction_per_extra_roi_sample": 0.000021794438
        },
        {
          "policy_id": "imported_trust",
          "label": "Imported trust",
          "total_samples": 30720,
          "overall_mae": 0.002884173,
          "overall_rmse": 0.018637586,
          "roi_mae": 0.031843167,
          "roi_rmse": 0.031843167,
          "non_roi_mae": 0.0028822876,
          "non_roi_rmse": 0.018636422,
          "roi_mean_spp": 12.0,
          "non_roi_mean_spp": 1.9993489,
          "max_spp": 12,
          "allocation_concentration": 6.001954,
          "extra_roi_samples_vs_uniform": 10.0,
          "roi_error_reduction_per_extra_roi_sample": 0.014041652
        },
        {
          "policy_id": "hybrid_trust_variance",
          "label": "Hybrid trust + variance",
          "total_samples": 30720,
          "overall_mae": 0.0026189247,
          "overall_rmse": 0.017040124,
          "roi_mae": 0.17199929,
          "roi_rmse": 0.17199929,
          "non_roi_mae": 0.0026078962,
          "non_roi_rmse": 0.016984068,
          "roi_mean_spp": 5.0,
          "non_roi_mean_spp": 1.9998046,
          "max_spp": 6,
          "allocation_concentration": 2.5002441,
          "extra_roi_samples_vs_uniform": 3.0,
          "roi_error_reduction_per_extra_roi_sample": 0.000086799264
        }
      ],
      "headline": "Thin-Structure Reveal: imported-trust ROI MAE 0.03184, combined-heuristic ROI MAE 0.04977, uniform ROI MAE 0.17226.",
      "bounded_note": "Imported trust remains competitive under equal budget on this scenario."
    },
    {
      "scenario_id": "fast_pan",
      "scenario_title": "Fast Lateral Reveal",
      "expectation": "BenefitExpected",
      "support_category": "RegionRoi",
      "sampling_taxonomy": "thin-band reveal with textured background",
      "demo_b_taxonomy": "mixed",
      "onset_frame": 4,
      "target_label": "fast-pan reveal region",
      "target_pixels": 644,
      "policies": [
        {
          "policy_id": "uniform",
          "label": "Uniform",
          "total_samples": 30720,
          "overall_mae": 0.005139688,
          "overall_rmse": 0.020593327,
          "roi_mae": 0.008036769,
          "roi_rmse": 0.030337619,
          "non_roi_mae": 0.005012916,
          "non_roi_rmse": 0.0200591,
          "roi_mean_spp": 2.0,
          "non_roi_mean_spp": 2.0,
          "max_spp": 2,
          "allocation_concentration": 1.0,
          "extra_roi_samples_vs_uniform": 0.0,
          "roi_error_reduction_per_extra_roi_sample": 0.0
        },
        {
          "policy_id": "edge_guided",
          "label": "Edge-guided",
          "total_samples": 30720,
          "overall_mae": 0.00426012,
          "overall_rmse": 0.01248663,
          "roi_mae": 0.005770245,
          "roi_rmse": 0.016678905,
          "non_roi_mae": 0.0041940343,
          "non_roi_rmse": 0.012270519,
          "roi_mean_spp": 2.64441,
          "non_roi_mean_spp": 1.9717994,
          "max_spp": 10,
          "allocation_concentration": 1.3411151,
          "extra_roi_samples_vs_uniform": 0.6444099,
          "roi_error_reduction_per_extra_roi_sample": 0.0035172084
        },
        {
          "policy_id": "residual_guided",
          "label": "Residual-guided",
          "total_samples": 30720,
          "overall_mae": 0.0043330565,
          "overall_rmse": 0.013700697,
          "roi_mae": 0.006092304,
          "roi_rmse": 0.017265866,
          "non_roi_mae": 0.004256081,
          "non_roi_rmse": 0.013523274,
          "roi_mean_spp": 2.2763975,
          "non_roi_mean_spp": 1.9879043,
          "max_spp": 12,
          "allocation_concentration": 1.1451243,
          "extra_roi_samples_vs_uniform": 0.27639747,
          "roi_error_reduction_per_extra_roi_sample": 0.0070350324
        },
        {
          "policy_id": "contrast_guided",
          "label": "Contrast-guided",
          "total_samples": 30720,
          "overall_mae": 0.0041318117,
          "overall_rmse": 0.011467859,
          "roi_mae": 0.0053702006,
          "roi_rmse": 0.015233616,
          "non_roi_mae": 0.004077619,
          "non_roi_rmse": 0.0112743825,
          "roi_mean_spp": 2.7298136,
          "non_roi_mean_spp": 1.9680619,
          "max_spp": 8,
          "allocation_concentration": 1.3870567,
          "extra_roi_samples_vs_uniform": 0.7298136,
          "roi_error_reduction_per_extra_roi_sample": 0.0036537666
        },
        {
          "policy_id": "variance_guided",
          "label": "Variance-guided",
          "total_samples": 30720,
          "overall_mae": 0.004936533,
          "overall_rmse": 0.020670475,
          "roi_mae": 0.007929652,
          "roi_rmse": 0.029893475,
          "non_roi_mae": 0.004805561,
          "non_roi_rmse": 0.020170799,
          "roi_mean_spp": 2.068323,
          "non_roi_mean_spp": 1.9970101,
          "max_spp": 12,
          "allocation_concentration": 1.0357097,
          "extra_roi_samples_vs_uniform": 0.0683229,
          "roi_error_reduction_per_extra_roi_sample": 0.0015678053
        },
        {
          "policy_id": "combined_heuristic",
          "label": "Combined heuristic",
          "total_samples": 30720,
          "overall_mae": 0.004081705,
          "overall_rmse": 0.011639646,
          "roi_mae": 0.0060267006,
          "roi_rmse": 0.017756527,
          "non_roi_mae": 0.0039965888,
          "non_roi_rmse": 0.011296646,
          "roi_mean_spp": 2.4099379,
          "non_roi_mean_spp": 1.9820603,
          "max_spp": 12,
          "allocation_concentration": 1.2158751,
          "extra_roi_samples_vs_uniform": 0.40993786,
          "roi_error_reduction_per_extra_roi_sample": 0.004903349
        },
        {
          "policy_id": "native_trust",
          "label": "Native trust",
          "total_samples": 30720,
          "overall_mae": 0.004122688,
          "overall_rmse": 0.011900045,
          "roi_mae": 0.0062935613,
          "roi_rmse": 0.018930092,
          "non_roi_mae": 0.004027689,
          "non_roi_rmse": 0.011494718,
          "roi_mean_spp": 2.2934783,
          "non_roi_mean_spp": 1.9871569,
          "max_spp": 12,
          "allocation_concentration": 1.1541506,
          "extra_roi_samples_vs_uniform": 0.29347825,
          "roi_error_reduction_per_extra_roi_sample": 0.005939819
        },
        {
          "policy_id": "imported_trust",
          "label": "Imported trust",
          "total_samples": 30720,
          "overall_mae": 0.005481308,
          "overall_rmse": 0.020067478,
          "roi_mae": 0.002196287,
          "roi_rmse": 0.008961542,
          "non_roi_mae": 0.0056250673,
          "non_roi_rmse": 0.020415975,
          "roi_mean_spp": 11.178572,
          "non_roi_mean_spp": 1.5983284,
          "max_spp": 12,
          "allocation_concentration": 6.9939146,
          "extra_roi_samples_vs_uniform": 9.178572,
          "roi_error_reduction_per_extra_roi_sample": 0.0006363171
        },
        {
          "policy_id": "hybrid_trust_variance",
          "label": "Hybrid trust + variance",
          "total_samples": 30720,
          "overall_mae": 0.004899455,
          "overall_rmse": 0.018562187,
          "roi_mae": 0.0038108004,
          "roi_rmse": 0.013789066,
          "non_roi_mae": 0.004947098,
          "non_roi_rmse": 0.018743359,
          "roi_mean_spp": 5.060559,
          "non_roi_mean_spp": 1.8660642,
          "max_spp": 12,
          "allocation_concentration": 2.711889,
          "extra_roi_samples_vs_uniform": 3.0605588,
          "roi_error_reduction_per_extra_roi_sample": 0.0013807833
        }
      ],
      "headline": "Fast Lateral Reveal: imported-trust ROI MAE 0.00220, combined-heuristic ROI MAE 0.00603, uniform ROI MAE 0.00804.",
      "bounded_note": "Imported trust remains competitive under equal budget on this scenario."
    },
    {
      "scenario_id": "diagonal_reveal",
      "scenario_title": "Diagonal Subpixel Reveal",
      "expectation": "BenefitExpected",
      "support_category": "PointLikeRoi",
      "sampling_taxonomy": "subpixel diagonal coverage case",
      "demo_b_taxonomy": "aliasing_limited",
      "onset_frame": 5,
      "target_label": "diagonal thin reveal",
      "target_pixels": 1,
      "policies": [
        {
          "policy_id": "uniform",
          "label": "Uniform",
          "total_samples": 30720,
          "overall_mae": 0.006755277,
          "overall_rmse": 0.012197416,
          "roi_mae": 0.01606533,
          "roi_rmse": 0.01606533,
          "non_roi_mae": 0.0067546717,
          "non_roi_rmse": 0.012197127,
          "roi_mean_spp": 2.0,
          "non_roi_mean_spp": 2.0,
          "max_spp": 2,
          "allocation_concentration": 1.0,
          "extra_roi_samples_vs_uniform": 0.0,
          "roi_error_reduction_per_extra_roi_sample": 0.0
        },
        {
          "policy_id": "edge_guided",
          "label": "Edge-guided",
          "total_samples": 30720,
          "overall_mae": 0.0061972043,
          "overall_rmse": 0.010818332,
          "roi_mae": 0.005273784,
          "roi_rmse": 0.005273784,
          "non_roi_mae": 0.006197265,
          "non_roi_rmse": 0.010818601,
          "roi_mean_spp": 8.0,
          "non_roi_mean_spp": 1.9996094,
          "max_spp": 8,
          "allocation_concentration": 4.0007815,
          "extra_roi_samples_vs_uniform": 6.0,
          "roi_error_reduction_per_extra_roi_sample": 0.001798591
        },
        {
          "policy_id": "residual_guided",
          "label": "Residual-guided",
          "total_samples": 30720,
          "overall_mae": 0.0065838415,
          "overall_rmse": 0.011597353,
          "roi_mae": 0.007956207,
          "roi_rmse": 0.007956207,
          "non_roi_mae": 0.0065837516,
          "non_roi_rmse": 0.011597553,
          "roi_mean_spp": 3.0,
          "non_roi_mean_spp": 1.9999349,
          "max_spp": 12,
          "allocation_concentration": 1.5000489,
          "extra_roi_samples_vs_uniform": 1.0,
          "roi_error_reduction_per_extra_roi_sample": 0.0081091225
        },
        {
          "policy_id": "contrast_guided",
          "label": "Contrast-guided",
          "total_samples": 30720,
          "overall_mae": 0.0063478067,
          "overall_rmse": 0.011162149,
          "roi_mae": 0.012427057,
          "roi_rmse": 0.012427057,
          "non_roi_mae": 0.0063474113,
          "non_roi_rmse": 0.011162062,
          "roi_mean_spp": 4.0,
          "non_roi_mean_spp": 1.9998698,
          "max_spp": 4,
          "allocation_concentration": 2.0001302,
          "extra_roi_samples_vs_uniform": 2.0,
          "roi_error_reduction_per_extra_roi_sample": 0.0018191361
        },
        {
          "policy_id": "variance_guided",
          "label": "Variance-guided",
          "total_samples": 30720,
          "overall_mae": 0.0065937922,
          "overall_rmse": 0.011762872,
          "roi_mae": 0.01606533,
          "roi_rmse": 0.01606533,
          "non_roi_mae": 0.006593175,
          "non_roi_rmse": 0.011762541,
          "roi_mean_spp": 2.0,
          "non_roi_mean_spp": 2.0,
          "max_spp": 12,
          "allocation_concentration": 1.0,
          "extra_roi_samples_vs_uniform": 0.0,
          "roi_error_reduction_per_extra_roi_sample": 0.0
        },
        {
          "policy_id": "combined_heuristic",
          "label": "Combined heuristic",
          "total_samples": 30720,
          "overall_mae": 0.0061927023,
          "overall_rmse": 0.0106852325,
          "roi_mae": 0.012448907,
          "roi_rmse": 0.012448907,
          "non_roi_mae": 0.0061922963,
          "non_roi_rmse": 0.010685108,
          "roi_mean_spp": 5.0,
          "non_roi_mean_spp": 1.9998046,
          "max_spp": 10,
          "allocation_concentration": 2.5002441,
          "extra_roi_samples_vs_uniform": 3.0,
          "roi_error_reduction_per_extra_roi_sample": 0.0012054741
        },
        {
          "policy_id": "native_trust",
          "label": "Native trust",
          "total_samples": 30720,
          "overall_mae": 0.0062505957,
          "overall_rmse": 0.0108382385,
          "roi_mae": 0.012427057,
          "roi_rmse": 0.012427057,
          "non_roi_mae": 0.006250193,
          "non_roi_rmse": 0.010838128,
          "roi_mean_spp": 4.0,
          "non_roi_mean_spp": 1.9998698,
          "max_spp": 12,
          "allocation_concentration": 2.0001302,
          "extra_roi_samples_vs_uniform": 2.0,
          "roi_error_reduction_per_extra_roi_sample": 0.0018191361
        },
        {
          "policy_id": "imported_trust",
          "label": "Imported trust",
          "total_samples": 30720,
          "overall_mae": 0.0067899795,
          "overall_rmse": 0.012261096,
          "roi_mae": 0.007695814,
          "roi_rmse": 0.007695814,
          "non_roi_mae": 0.006789921,
          "non_roi_rmse": 0.0122613385,
          "roi_mean_spp": 12.0,
          "non_roi_mean_spp": 1.9993489,
          "max_spp": 12,
          "allocation_concentration": 6.001954,
          "extra_roi_samples_vs_uniform": 10.0,
          "roi_error_reduction_per_extra_roi_sample": 0.0008369515
        },
        {
          "policy_id": "hybrid_trust_variance",
          "label": "Hybrid trust + variance",
          "total_samples": 30720,
          "overall_mae": 0.0066867056,
          "overall_rmse": 0.011856037,
          "roi_mae": 0.012448907,
          "roi_rmse": 0.012448907,
          "non_roi_mae": 0.0066863303,
          "non_roi_rmse": 0.011855997,
          "roi_mean_spp": 5.0,
          "non_roi_mean_spp": 1.9998046,
          "max_spp": 12,
          "allocation_concentration": 2.5002441,
          "extra_roi_samples_vs_uniform": 3.0,
          "roi_error_reduction_per_extra_roi_sample": 0.0012054741
        }
      ],
      "headline": "Diagonal Subpixel Reveal: imported-trust ROI MAE 0.00770, combined-heuristic ROI MAE 0.01245, uniform ROI MAE 0.01607.",
      "bounded_note": "Imported trust remains competitive under equal budget on this scenario."
    },
    {
      "scenario_id": "reveal_band",
      "scenario_title": "Textured Reveal Band",
      "expectation": "BenefitExpected",
      "support_category": "RegionRoi",
      "sampling_taxonomy": "mixed-width reveal band with aliasing and texture",
      "demo_b_taxonomy": "mixed",
      "onset_frame": 5,
      "target_label": "textured reveal band",
      "target_pixels": 156,
      "policies": [
        {
          "policy_id": "uniform",
          "label": "Uniform",
          "total_samples": 30720,
          "overall_mae": 0.010161891,
          "overall_rmse": 0.028897643,
          "roi_mae": 0.014585863,
          "roi_rmse": 0.034710594,
          "non_roi_mae": 0.010116502,
          "non_roi_rmse": 0.028831936,
          "roi_mean_spp": 2.0,
          "non_roi_mean_spp": 2.0,
          "max_spp": 2,
          "allocation_concentration": 1.0,
          "extra_roi_samples_vs_uniform": 0.0,
          "roi_error_reduction_per_extra_roi_sample": 0.0
        },
        {
          "policy_id": "edge_guided",
          "label": "Edge-guided",
          "total_samples": 30720,
          "overall_mae": 0.0073653716,
          "overall_rmse": 0.017138181,
          "roi_mae": 0.010750462,
          "roi_rmse": 0.020568417,
          "non_roi_mae": 0.0073306356,
          "non_roi_rmse": 0.017099414,
          "roi_mean_spp": 3.3589745,
          "non_roi_mean_spp": 1.9860563,
          "max_spp": 6,
          "allocation_concentration": 1.6912786,
          "extra_roi_samples_vs_uniform": 1.3589745,
          "roi_error_reduction_per_extra_roi_sample": 0.0028222757
        },
        {
          "policy_id": "residual_guided",
          "label": "Residual-guided",
          "total_samples": 30720,
          "overall_mae": 0.0076889875,
          "overall_rmse": 0.018935258,
          "roi_mae": 0.011239121,
          "roi_rmse": 0.025510825,
          "non_roi_mae": 0.0076525644,
          "non_roi_rmse": 0.018855905,
          "roi_mean_spp": 2.5576923,
          "non_roi_mean_spp": 1.9942778,
          "max_spp": 9,
          "allocation_concentration": 1.2825155,
          "extra_roi_samples_vs_uniform": 0.5576923,
          "roi_error_reduction_per_extra_roi_sample": 0.0060010552
        },
        {
          "policy_id": "contrast_guided",
          "label": "Contrast-guided",
          "total_samples": 30720,
          "overall_mae": 0.0073950784,
          "overall_rmse": 0.017897889,
          "roi_mae": 0.009286027,
          "roi_rmse": 0.017734658,
          "non_roi_mae": 0.007375676,
          "non_roi_rmse": 0.017899558,
          "roi_mean_spp": 3.1666667,
          "non_roi_mean_spp": 1.9880295,
          "max_spp": 5,
          "allocation_concentration": 1.5928671,
          "extra_roi_samples_vs_uniform": 1.1666667,
          "roi_error_reduction_per_extra_roi_sample": 0.004542716
        },
        {
          "policy_id": "variance_guided",
          "label": "Variance-guided",
          "total_samples": 30720,
          "overall_mae": 0.008172061,
          "overall_rmse": 0.021558823,
          "roi_mae": 0.011745246,
          "roi_rmse": 0.024126047,
          "non_roi_mae": 0.008135399,
          "non_roi_rmse": 0.021530896,
          "roi_mean_spp": 2.2179487,
          "non_roi_mean_spp": 1.9977638,
          "max_spp": 12,
          "allocation_concentration": 1.1102157,
          "extra_roi_samples_vs_uniform": 0.21794868,
          "roi_error_reduction_per_extra_roi_sample": 0.013033421
        },
        {
          "policy_id": "combined_heuristic",
          "label": "Combined heuristic",
          "total_samples": 30720,
          "overall_mae": 0.0072609023,
          "overall_rmse": 0.017378885,
          "roi_mae": 0.009719432,
          "roi_rmse": 0.018143332,
          "non_roi_mae": 0.0072356774,
          "non_roi_rmse": 0.017370872,
          "roi_mean_spp": 3.0448718,
          "non_roi_mean_spp": 1.9892792,
          "max_spp": 8,
          "allocation_concentration": 1.5306408,
          "extra_roi_samples_vs_uniform": 1.0448718,
          "roi_error_reduction_per_extra_roi_sample": 0.0046574427
        },
        {
          "policy_id": "native_trust",
          "label": "Native trust",
          "total_samples": 30720,
          "overall_mae": 0.00733864,
          "overall_rmse": 0.01793313,
          "roi_mae": 0.00931733,
          "roi_rmse": 0.015778635,
          "non_roi_mae": 0.007318338,
          "non_roi_rmse": 0.017953899,
          "roi_mean_spp": 2.8269231,
          "non_roi_mean_spp": 1.9915154,
          "max_spp": 10,
          "allocation_concentration": 1.4194834,
          "extra_roi_samples_vs_uniform": 0.82692313,
          "roi_error_reduction_per_extra_roi_sample": 0.0063712485
        },
        {
          "policy_id": "imported_trust",
          "label": "Imported trust",
          "total_samples": 30720,
          "overall_mae": 0.010154004,
          "overall_rmse": 0.0287292,
          "roi_mae": 0.0034279888,
          "roi_rmse": 0.0093814405,
          "non_roi_mae": 0.010223012,
          "non_roi_rmse": 0.028860578,
          "roi_mean_spp": 12.0,
          "non_roi_mean_spp": 1.8973954,
          "max_spp": 12,
          "allocation_concentration": 6.3244596,
          "extra_roi_samples_vs_uniform": 10.0,
          "roi_error_reduction_per_extra_roi_sample": 0.0011157874
        },
        {
          "policy_id": "hybrid_trust_variance",
          "label": "Hybrid trust + variance",
          "total_samples": 30720,
          "overall_mae": 0.00880657,
          "overall_rmse": 0.023271156,
          "roi_mae": 0.0053313943,
          "roi_rmse": 0.011944953,
          "non_roi_mae": 0.008842225,
          "non_roi_rmse": 0.023358922,
          "roi_mean_spp": 6.1410255,
          "non_roi_mean_spp": 1.9575112,
          "max_spp": 12,
          "allocation_concentration": 3.1371598,
          "extra_roi_samples_vs_uniform": 4.1410255,
          "roi_error_reduction_per_extra_roi_sample": 0.0022348254
        }
      ],
      "headline": "Textured Reveal Band: imported-trust ROI MAE 0.00343, combined-heuristic ROI MAE 0.00972, uniform ROI MAE 0.01459.",
      "bounded_note": "Imported trust remains competitive under equal budget on this scenario."
    },
    {
      "scenario_id": "motion_bias_band",
      "scenario_title": "Motion-Bias Reveal Band",
      "expectation": "BenefitExpected",
      "support_category": "RegionRoi",
      "sampling_taxonomy": "motion-mismatch reveal band",
      "demo_b_taxonomy": "mixed",
      "onset_frame": 6,
      "target_label": "motion-bias reveal band",
      "target_pixels": 714,
      "policies": [
        {
          "policy_id": "uniform",
          "label": "Uniform",
          "total_samples": 30720,
          "overall_mae": 0.009830369,
          "overall_rmse": 0.027760219,
          "roi_mae": 0.03228638,
          "roi_rmse": 0.05638643,
          "non_roi_mae": 0.008735619,
          "non_roi_rmse": 0.025557822,
          "roi_mean_spp": 2.0,
          "non_roi_mean_spp": 2.0,
          "max_spp": 2,
          "allocation_concentration": 1.0,
          "extra_roi_samples_vs_uniform": 0.0,
          "roi_error_reduction_per_extra_roi_sample": 0.0
        },
        {
          "policy_id": "edge_guided",
          "label": "Edge-guided",
          "total_samples": 30720,
          "overall_mae": 0.007169038,
          "overall_rmse": 0.016274104,
          "roi_mae": 0.017116146,
          "roi_rmse": 0.031873707,
          "non_roi_mae": 0.0066841193,
          "non_roi_rmse": 0.015107422,
          "roi_mean_spp": 4.2282915,
          "non_roi_mean_spp": 1.8913697,
          "max_spp": 6,
          "allocation_concentration": 2.2355711,
          "extra_roi_samples_vs_uniform": 2.2282915,
          "roi_error_reduction_per_extra_roi_sample": 0.006808011
        },
        {
          "policy_id": "residual_guided",
          "label": "Residual-guided",
          "total_samples": 30720,
          "overall_mae": 0.0072387503,
          "overall_rmse": 0.017150128,
          "roi_mae": 0.018428203,
          "roi_rmse": 0.03367304,
          "non_roi_mae": 0.006693274,
          "non_roi_rmse": 0.015912017,
          "roi_mean_spp": 4.165266,
          "non_roi_mean_spp": 1.8944422,
          "max_spp": 8,
          "allocation_concentration": 2.1986768,
          "extra_roi_samples_vs_uniform": 2.165266,
          "roi_error_reduction_per_extra_roi_sample": 0.006400219
        },
        {
          "policy_id": "contrast_guided",
          "label": "Contrast-guided",
          "total_samples": 30720,
          "overall_mae": 0.0072300737,
          "overall_rmse": 0.017004307,
          "roi_mae": 0.017020024,
          "roi_rmse": 0.0331406,
          "non_roi_mae": 0.006752822,
          "non_roi_rmse": 0.015802016,
          "roi_mean_spp": 4.02521,
          "non_roi_mean_spp": 1.9012699,
          "max_spp": 5,
          "allocation_concentration": 2.1171165,
          "extra_roi_samples_vs_uniform": 2.02521,
          "roi_error_reduction_per_extra_roi_sample": 0.0075381594
        },
        {
          "policy_id": "variance_guided",
          "label": "Variance-guided",
          "total_samples": 30720,
          "overall_mae": 0.0079818955,
          "overall_rmse": 0.021294275,
          "roi_mae": 0.024130555,
          "roi_rmse": 0.044468485,
          "non_roi_mae": 0.0071946466,
          "non_roi_rmse": 0.019471811,
          "roi_mean_spp": 2.885154,
          "non_roi_mean_spp": 1.9568483,
          "max_spp": 12,
          "allocation_concentration": 1.4743882,
          "extra_roi_samples_vs_uniform": 0.885154,
          "roi_error_reduction_per_extra_roi_sample": 0.009214018
        },
        {
          "policy_id": "combined_heuristic",
          "label": "Combined heuristic",
          "total_samples": 30720,
          "overall_mae": 0.0069546294,
          "overall_rmse": 0.01638144,
          "roi_mae": 0.01715514,
          "roi_rmse": 0.03184914,
          "non_roi_mae": 0.0064573577,
          "non_roi_rmse": 0.015231111,
          "roi_mean_spp": 4.0280113,
          "non_roi_mean_spp": 1.9011334,
          "max_spp": 8,
          "allocation_concentration": 2.118742,
          "extra_roi_samples_vs_uniform": 2.0280113,
          "roi_error_reduction_per_extra_roi_sample": 0.0074611213
        },
        {
          "policy_id": "native_trust",
          "label": "Native trust",
          "total_samples": 30720,
          "overall_mae": 0.00706014,
          "overall_rmse": 0.016907243,
          "roi_mae": 0.017891984,
          "roi_rmse": 0.032915123,
          "non_roi_mae": 0.006532084,
          "non_roi_rmse": 0.015715515,
          "roi_mean_spp": 3.7857144,
          "non_roi_mean_spp": 1.9129455,
          "max_spp": 9,
          "allocation_concentration": 1.9789975,
          "extra_roi_samples_vs_uniform": 1.7857144,
          "roi_error_reduction_per_extra_roi_sample": 0.00806086
        },
        {
          "policy_id": "imported_trust",
          "label": "Imported trust",
          "total_samples": 30720,
          "overall_mae": 0.008383384,
          "overall_rmse": 0.021967437,
          "roi_mae": 0.009735676,
          "roi_rmse": 0.019428289,
          "non_roi_mae": 0.008317468,
          "non_roi_rmse": 0.022083763,
          "roi_mean_spp": 7.214286,
          "non_roi_mean_spp": 1.7458009,
          "max_spp": 8,
          "allocation_concentration": 4.1323647,
          "extra_roi_samples_vs_uniform": 5.214286,
          "roi_error_reduction_per_extra_roi_sample": 0.004324792
        },
        {
          "policy_id": "hybrid_trust_variance",
          "label": "Hybrid trust + variance",
          "total_samples": 30720,
          "overall_mae": 0.007619438,
          "overall_rmse": 0.019997815,
          "roi_mae": 0.014983777,
          "roi_rmse": 0.029766746,
          "non_roi_mae": 0.007260423,
          "non_roi_rmse": 0.019396206,
          "roi_mean_spp": 4.910364,
          "non_roi_mean_spp": 1.8581183,
          "max_spp": 12,
          "allocation_concentration": 2.6426542,
          "extra_roi_samples_vs_uniform": 2.9103642,
          "roi_error_reduction_per_extra_roi_sample": 0.0059451675
        }
      ],
      "headline": "Motion-Bias Reveal Band: imported-trust ROI MAE 0.00974, combined-heuristic ROI MAE 0.01716, uniform ROI MAE 0.03229.",
      "bounded_note": "Imported trust remains competitive under equal budget on this scenario."
    },
    {
      "scenario_id": "layered_slats",
      "scenario_title": "Layered Slat Reveal",
      "expectation": "BenefitExpected",
      "support_category": "RegionRoi",
      "sampling_taxonomy": "layered slat reveal with mixed stable and unstable zones",
      "demo_b_taxonomy": "mixed",
      "onset_frame": 5,
      "target_label": "layered slat reveal",
      "target_pixels": 162,
      "policies": [
        {
          "policy_id": "uniform",
          "label": "Uniform",
          "total_samples": 30720,
          "overall_mae": 0.009732364,
          "overall_rmse": 0.027715582,
          "roi_mae": 0.019847455,
          "roi_rmse": 0.042561185,
          "non_roi_mae": 0.009624544,
          "non_roi_rmse": 0.027514232,
          "roi_mean_spp": 2.0,
          "non_roi_mean_spp": 2.0,
          "max_spp": 2,
          "allocation_concentration": 1.0,
          "extra_roi_samples_vs_uniform": 0.0,
          "roi_error_reduction_per_extra_roi_sample": 0.0
        },
        {
          "policy_id": "edge_guided",
          "label": "Edge-guided",
          "total_samples": 30720,
          "overall_mae": 0.00707087,
          "overall_rmse": 0.016754318,
          "roi_mae": 0.00958756,
          "roi_rmse": 0.01785354,
          "non_roi_mae": 0.0070440467,
          "non_roi_rmse": 0.016742218,
          "roi_mean_spp": 4.648148,
          "non_roi_mean_spp": 1.9717726,
          "max_spp": 6,
          "allocation_concentration": 2.3573449,
          "extra_roi_samples_vs_uniform": 2.648148,
          "roi_error_reduction_per_extra_roi_sample": 0.003874366
        },
        {
          "policy_id": "residual_guided",
          "label": "Residual-guided",
          "total_samples": 30720,
          "overall_mae": 0.0073866546,
          "overall_rmse": 0.018361023,
          "roi_mae": 0.010367473,
          "roi_rmse": 0.019426363,
          "non_roi_mae": 0.007354878,
          "non_roi_rmse": 0.018349335,
          "roi_mean_spp": 4.5246916,
          "non_roi_mean_spp": 1.9730886,
          "max_spp": 9,
          "allocation_concentration": 2.2932024,
          "extra_roi_samples_vs_uniform": 2.5246916,
          "roi_error_reduction_per_extra_roi_sample": 0.0037549068
        },
        {
          "policy_id": "contrast_guided",
          "label": "Contrast-guided",
          "total_samples": 30720,
          "overall_mae": 0.0070707495,
          "overall_rmse": 0.01733359,
          "roi_mae": 0.009950254,
          "roi_rmse": 0.020127594,
          "non_roi_mae": 0.007040059,
          "non_roi_rmse": 0.017301382,
          "roi_mean_spp": 4.080247,
          "non_roi_mean_spp": 1.977826,
          "max_spp": 5,
          "allocation_concentration": 2.062996,
          "extra_roi_samples_vs_uniform": 2.080247,
          "roi_error_reduction_per_extra_roi_sample": 0.0047577047
        },
        {
          "policy_id": "variance_guided",
          "label": "Variance-guided",
          "total_samples": 30720,
          "overall_mae": 0.007928443,
          "overall_rmse": 0.020998163,
          "roi_mae": 0.016817346,
          "roi_rmse": 0.03674163,
          "non_roi_mae": 0.007833693,
          "non_roi_rmse": 0.020766154,
          "roi_mean_spp": 2.3580246,
          "non_roi_mean_spp": 1.9961838,
          "max_spp": 12,
          "allocation_concentration": 1.1812663,
          "extra_roi_samples_vs_uniform": 0.3580246,
          "roi_error_reduction_per_extra_roi_sample": 0.008463408
        },
        {
          "policy_id": "combined_heuristic",
          "label": "Combined heuristic",
          "total_samples": 30720,
          "overall_mae": 0.0069223046,
          "overall_rmse": 0.016815796,
          "roi_mae": 0.008812139,
          "roi_rmse": 0.01602421,
          "non_roi_mae": 0.0069021652,
          "non_roi_rmse": 0.016824037,
          "roi_mean_spp": 4.339506,
          "non_roi_mean_spp": 1.9750625,
          "max_spp": 8,
          "allocation_concentration": 2.1971488,
          "extra_roi_samples_vs_uniform": 2.3395061,
          "roi_error_reduction_per_extra_roi_sample": 0.0047169426
        },
        {
          "policy_id": "native_trust",
          "label": "Native trust",
          "total_samples": 30720,
          "overall_mae": 0.007035849,
          "overall_rmse": 0.017518803,
          "roi_mae": 0.010175551,
          "roi_rmse": 0.021932108,
          "non_roi_mae": 0.00700238,
          "non_roi_rmse": 0.017465752,
          "roi_mean_spp": 3.9444444,
          "non_roi_mean_spp": 1.9792736,
          "max_spp": 10,
          "allocation_concentration": 1.9928749,
          "extra_roi_samples_vs_uniform": 1.9444444,
          "roi_error_reduction_per_extra_roi_sample": 0.0049741217
        },
        {
          "policy_id": "imported_trust",
          "label": "Imported trust",
          "total_samples": 30720,
          "overall_mae": 0.009672378,
          "overall_rmse": 0.027414657,
          "roi_mae": 0.0035278392,
          "roi_rmse": 0.008651957,
          "non_roi_mae": 0.009737871,
          "non_roi_rmse": 0.027545903,
          "roi_mean_spp": 12.0,
          "non_roi_mean_spp": 1.893407,
          "max_spp": 12,
          "allocation_concentration": 6.3377814,
          "extra_roi_samples_vs_uniform": 10.0,
          "roi_error_reduction_per_extra_roi_sample": 0.0016319616
        },
        {
          "policy_id": "hybrid_trust_variance",
          "label": "Hybrid trust + variance",
          "total_samples": 30720,
          "overall_mae": 0.008410004,
          "overall_rmse": 0.022263901,
          "roi_mae": 0.007625702,
          "roi_rmse": 0.018620735,
          "non_roi_mae": 0.00841835,
          "non_roi_rmse": 0.02229953,
          "roi_mean_spp": 6.111111,
          "non_roi_mean_spp": 1.9561784,
          "max_spp": 12,
          "allocation_concentration": 3.124005,
          "extra_roi_samples_vs_uniform": 4.111111,
          "roi_error_reduction_per_extra_roi_sample": 0.0029728587
        }
      ],
      "headline": "Layered Slat Reveal: imported-trust ROI MAE 0.00353, combined-heuristic ROI MAE 0.00881, uniform ROI MAE 0.01985.",
      "bounded_note": "Imported trust remains competitive under equal budget on this scenario."
    },
    {
      "scenario_id": "noisy_reprojection",
      "scenario_title": "Noisy Reprojection Reveal",
      "expectation": "BenefitExpected",
      "support_category": "RegionRoi",
      "sampling_taxonomy": "realism-stress reveal with noisy reprojection",
      "demo_b_taxonomy": "variance_limited",
      "onset_frame": 6,
      "target_label": "noisy reprojection reveal",
      "target_pixels": 1658,
      "policies": [
        {
          "policy_id": "uniform",
          "label": "Uniform",
          "total_samples": 30720,
          "overall_mae": 0.009424537,
          "overall_rmse": 0.026225172,
          "roi_mae": 0.03289715,
          "roi_rmse": 0.056972872,
          "non_roi_mae": 0.00658423,
          "non_roi_rmse": 0.019447815,
          "roi_mean_spp": 2.0,
          "non_roi_mean_spp": 2.0,
          "max_spp": 2,
          "allocation_concentration": 1.0,
          "extra_roi_samples_vs_uniform": 0.0,
          "roi_error_reduction_per_extra_roi_sample": 0.0
        },
        {
          "policy_id": "edge_guided",
          "label": "Edge-guided",
          "total_samples": 30720,
          "overall_mae": 0.0071613295,
          "overall_rmse": 0.01635494,
          "roi_mae": 0.020666149,
          "roi_rmse": 0.03786961,
          "non_roi_mae": 0.0055272123,
          "non_roi_rmse": 0.011239504,
          "roi_mean_spp": 4.00965,
          "non_roi_mean_spp": 1.7568238,
          "max_spp": 6,
          "allocation_concentration": 2.2823293,
          "extra_roi_samples_vs_uniform": 2.0096502,
          "roi_error_reduction_per_extra_roi_sample": 0.0060861334
        },
        {
          "policy_id": "residual_guided",
          "label": "Residual-guided",
          "total_samples": 30720,
          "overall_mae": 0.007233794,
          "overall_rmse": 0.017139282,
          "roi_mae": 0.022310998,
          "roi_rmse": 0.04028462,
          "non_roi_mae": 0.005409402,
          "non_roi_rmse": 0.011529847,
          "roi_mean_spp": 3.8799758,
          "non_roi_mean_spp": 1.7725149,
          "max_spp": 8,
          "allocation_concentration": 2.1889665,
          "extra_roi_samples_vs_uniform": 1.8799758,
          "roi_error_reduction_per_extra_roi_sample": 0.0056310035
        },
        {
          "policy_id": "contrast_guided",
          "label": "Contrast-guided",
          "total_samples": 30720,
          "overall_mae": 0.0071405396,
          "overall_rmse": 0.016893908,
          "roi_mae": 0.019924378,
          "roi_rmse": 0.03827624,
          "non_roi_mae": 0.005593663,
          "non_roi_rmse": 0.0119443955,
          "roi_mean_spp": 3.9173703,
          "non_roi_mean_spp": 1.7679901,
          "max_spp": 5,
          "allocation_concentration": 2.2157197,
          "extra_roi_samples_vs_uniform": 1.9173703,
          "roi_error_reduction_per_extra_roi_sample": 0.006765918
        },
        {
          "policy_id": "variance_guided",
          "label": "Variance-guided",
          "total_samples": 30720,
          "overall_mae": 0.0077034435,
          "overall_rmse": 0.019935794,
          "roi_mae": 0.024089385,
          "roi_rmse": 0.04346564,
          "non_roi_mae": 0.005720671,
          "non_roi_rmse": 0.014728317,
          "roi_mean_spp": 2.8835948,
          "non_roi_mean_spp": 1.8930813,
          "max_spp": 12,
          "allocation_concentration": 1.5232282,
          "extra_roi_samples_vs_uniform": 0.88359475,
          "roi_error_reduction_per_extra_roi_sample": 0.009968103
        },
        {
          "policy_id": "combined_heuristic",
          "label": "Combined heuristic",
          "total_samples": 30720,
          "overall_mae": 0.006949845,
          "overall_rmse": 0.016237207,
          "roi_mae": 0.02066805,
          "roi_rmse": 0.03796535,
          "non_roi_mae": 0.005289913,
          "non_roi_rmse": 0.011006601,
          "roi_mean_spp": 3.876357,
          "non_roi_mean_spp": 1.7729528,
          "max_spp": 8,
          "allocation_concentration": 2.186385,
          "extra_roi_samples_vs_uniform": 1.8763571,
          "roi_error_reduction_per_extra_roi_sample": 0.0065174685
        },
        {
          "policy_id": "native_trust",
          "label": "Native trust",
          "total_samples": 30720,
          "overall_mae": 0.007011652,
          "overall_rmse": 0.016729234,
          "roi_mae": 0.021494558,
          "roi_rmse": 0.038817845,
          "non_roi_mae": 0.0052591874,
          "non_roi_rmse": 0.011463364,
          "roi_mean_spp": 3.601327,
          "non_roi_mean_spp": 1.8062327,
          "max_spp": 9,
          "allocation_concentration": 1.9938333,
          "extra_roi_samples_vs_uniform": 1.601327,
          "roi_error_reduction_per_extra_roi_sample": 0.0071207136
        },
        {
          "policy_id": "imported_trust",
          "label": "Imported trust",
          "total_samples": 30720,
          "overall_mae": 0.007821716,
          "overall_rmse": 0.019544724,
          "roi_mae": 0.010562399,
          "roi_rmse": 0.020832058,
          "non_roi_mae": 0.007490069,
          "non_roi_rmse": 0.019383196,
          "roi_mean_spp": 7.027141,
          "non_roi_mean_spp": 1.3916947,
          "max_spp": 8,
          "allocation_concentration": 5.049341,
          "extra_roi_samples_vs_uniform": 5.027141,
          "roi_error_reduction_per_extra_roi_sample": 0.004442833
        },
        {
          "policy_id": "hybrid_trust_variance",
          "label": "Hybrid trust + variance",
          "total_samples": 30720,
          "overall_mae": 0.007026409,
          "overall_rmse": 0.017580751,
          "roi_mae": 0.01499264,
          "roi_rmse": 0.030081114,
          "non_roi_mae": 0.0060624504,
          "non_roi_rmse": 0.01539463,
          "roi_mean_spp": 4.779252,
          "non_roi_mean_spp": 1.6636987,
          "max_spp": 12,
          "allocation_concentration": 2.8726668,
          "extra_roi_samples_vs_uniform": 2.779252,
          "roi_error_reduction_per_extra_roi_sample": 0.006442204
        }
      ],
      "headline": "Noisy Reprojection Reveal: imported-trust ROI MAE 0.01056, combined-heuristic ROI MAE 0.02067, uniform ROI MAE 0.03290.",
      "bounded_note": "Imported trust remains competitive under equal budget on this scenario."
    },
    {
      "scenario_id": "heuristic_friendly_pan",
      "scenario_title": "Heuristic-Friendly Pan",
      "expectation": "BenefitExpected",
      "support_category": "RegionRoi",
      "sampling_taxonomy": "competitive baseline reveal",
      "demo_b_taxonomy": "edge_trap",
      "onset_frame": 4,
      "target_label": "heuristic-friendly reveal",
      "target_pixels": 576,
      "policies": [
        {
          "policy_id": "uniform",
          "label": "Uniform",
          "total_samples": 30720,
          "overall_mae": 0.006489886,
          "overall_rmse": 0.015525697,
          "roi_mae": 0.0102981515,
          "roi_rmse": 0.018510709,
          "non_roi_mae": 0.006341508,
          "non_roi_rmse": 0.015397695,
          "roi_mean_spp": 2.0,
          "non_roi_mean_spp": 2.0,
          "max_spp": 2,
          "allocation_concentration": 1.0,
          "extra_roi_samples_vs_uniform": 0.0,
          "roi_error_reduction_per_extra_roi_sample": 0.0
        },
        {
          "policy_id": "edge_guided",
          "label": "Edge-guided",
          "total_samples": 30720,
          "overall_mae": 0.0053066527,
          "overall_rmse": 0.010151311,
          "roi_mae": 0.0070037353,
          "roi_rmse": 0.009859078,
          "non_roi_mae": 0.005240536,
          "non_roi_rmse": 0.010162525,
          "roi_mean_spp": 3.703125,
          "non_roi_mean_spp": 1.9336445,
          "max_spp": 6,
          "allocation_concentration": 1.9151012,
          "extra_roi_samples_vs_uniform": 1.703125,
          "roi_error_reduction_per_extra_roi_sample": 0.0019343361
        },
        {
          "policy_id": "residual_guided",
          "label": "Residual-guided",
          "total_samples": 30720,
          "overall_mae": 0.0055203247,
          "overall_rmse": 0.011033349,
          "roi_mae": 0.0073533,
          "roi_rmse": 0.010719466,
          "non_roi_mae": 0.005448911,
          "non_roi_rmse": 0.011045399,
          "roi_mean_spp": 3.5329862,
          "non_roi_mean_spp": 1.9402733,
          "max_spp": 9,
          "allocation_concentration": 1.8208704,
          "extra_roi_samples_vs_uniform": 1.5329862,
          "roi_error_reduction_per_extra_roi_sample": 0.0019209902
        },
        {
          "policy_id": "contrast_guided",
          "label": "Contrast-guided",
          "total_samples": 30720,
          "overall_mae": 0.0052872403,
          "overall_rmse": 0.010421414,
          "roi_mae": 0.007278959,
          "roi_rmse": 0.010826499,
          "non_roi_mae": 0.0052096397,
          "non_roi_rmse": 0.010405311,
          "roi_mean_spp": 3.4184027,
          "non_roi_mean_spp": 1.9447376,
          "max_spp": 5,
          "allocation_concentration": 1.7577707,
          "extra_roi_samples_vs_uniform": 1.4184027,
          "roi_error_reduction_per_extra_roi_sample": 0.0021285864
        },
        {
          "policy_id": "variance_guided",
          "label": "Variance-guided",
          "total_samples": 30720,
          "overall_mae": 0.0055280444,
          "overall_rmse": 0.012075172,
          "roi_mae": 0.008754189,
          "roi_rmse": 0.014351064,
          "non_roi_mae": 0.005402355,
          "non_roi_rmse": 0.011977757,
          "roi_mean_spp": 2.3229167,
          "non_roi_mean_spp": 1.9874189,
          "max_spp": 12,
          "allocation_concentration": 1.1688108,
          "extra_roi_samples_vs_uniform": 0.32291675,
          "roi_error_reduction_per_extra_roi_sample": 0.0047813016
        },
        {
          "policy_id": "combined_heuristic",
          "label": "Combined heuristic",
          "total_samples": 30720,
          "overall_mae": 0.0051547694,
          "overall_rmse": 0.010126305,
          "roi_mae": 0.00691609,
          "roi_rmse": 0.010047597,
          "non_roi_mae": 0.0050861486,
          "non_roi_rmse": 0.010129358,
          "roi_mean_spp": 3.5434027,
          "non_roi_mean_spp": 1.9398674,
          "max_spp": 8,
          "allocation_concentration": 1.826621,
          "extra_roi_samples_vs_uniform": 1.5434027,
          "roi_error_reduction_per_extra_roi_sample": 0.0021913021
        },
        {
          "policy_id": "native_trust",
          "label": "Native trust",
          "total_samples": 30720,
          "overall_mae": 0.0051950756,
          "overall_rmse": 0.010348762,
          "roi_mae": 0.007112995,
          "roi_rmse": 0.010544254,
          "non_roi_mae": 0.005120349,
          "non_roi_rmse": 0.01034107,
          "roi_mean_spp": 3.2743056,
          "non_roi_mean_spp": 1.9503517,
          "max_spp": 10,
          "allocation_concentration": 1.6788282,
          "extra_roi_samples_vs_uniform": 1.2743056,
          "roi_error_reduction_per_extra_roi_sample": 0.0024995236
        },
        {
          "policy_id": "imported_trust",
          "label": "Imported trust",
          "total_samples": 30720,
          "overall_mae": 0.0066374904,
          "overall_rmse": 0.015451209,
          "roi_mae": 0.0025213864,
          "roi_rmse": 0.0050600283,
          "non_roi_mae": 0.0067978553,
          "non_roi_rmse": 0.015717633,
          "roi_mean_spp": 11.439236,
          "non_roi_mean_spp": 1.6322376,
          "max_spp": 12,
          "allocation_concentration": 7.0083156,
          "extra_roi_samples_vs_uniform": 9.439236,
          "roi_error_reduction_per_extra_roi_sample": 0.0008238766
        },
        {
          "policy_id": "hybrid_trust_variance",
          "label": "Hybrid trust + variance",
          "total_samples": 30720,
          "overall_mae": 0.0056750868,
          "overall_rmse": 0.012493149,
          "roi_mae": 0.0047482587,
          "roi_rmse": 0.008198086,
          "non_roi_mae": 0.0057111946,
          "non_roi_rmse": 0.012630964,
          "roi_mean_spp": 5.517361,
          "non_roi_mean_spp": 1.86296,
          "max_spp": 12,
          "allocation_concentration": 2.96161,
          "extra_roi_samples_vs_uniform": 3.5173612,
          "roi_error_reduction_per_extra_roi_sample": 0.001577857
        }
      ],
      "headline": "Heuristic-Friendly Pan: imported-trust ROI MAE 0.00252, combined-heuristic ROI MAE 0.00692, uniform ROI MAE 0.01030.",
      "bounded_note": "Imported trust remains competitive under equal budget on this scenario."
    },
    {
      "scenario_id": "contrast_pulse",
      "scenario_title": "Contrast Pulse Stress",
      "expectation": "NeutralExpected",
      "support_category": "NegativeControl",
      "sampling_taxonomy": "negative control",
      "demo_b_taxonomy": "variance_limited",
      "onset_frame": 0,
      "target_label": "pulse region",
      "target_pixels": 1872,
      "policies": [
        {
          "policy_id": "uniform",
          "label": "Uniform",
          "total_samples": 30720,
          "overall_mae": 0.00006458632,
          "overall_rmse": 0.000072489194,
          "roi_mae": 0.00007679083,
          "roi_rmse": 0.00008592822,
          "non_roi_mae": 0.00006289236,
          "non_roi_rmse": 0.000070421585,
          "roi_mean_spp": 2.0,
          "non_roi_mean_spp": 2.0,
          "max_spp": 2,
          "allocation_concentration": 1.0,
          "extra_roi_samples_vs_uniform": 0.0,
          "roi_error_reduction_per_extra_roi_sample": 0.0
        },
        {
          "policy_id": "edge_guided",
          "label": "Edge-guided",
          "total_samples": 30720,
          "overall_mae": 0.00006458632,
          "overall_rmse": 0.000072489194,
          "roi_mae": 0.00007679083,
          "roi_rmse": 0.00008592822,
          "non_roi_mae": 0.00006289236,
          "non_roi_rmse": 0.000070421585,
          "roi_mean_spp": 2.0,
          "non_roi_mean_spp": 2.0,
          "max_spp": 2,
          "allocation_concentration": 1.0,
          "extra_roi_samples_vs_uniform": 0.0,
          "roi_error_reduction_per_extra_roi_sample": 0.0
        },
        {
          "policy_id": "residual_guided",
          "label": "Residual-guided",
          "total_samples": 30720,
          "overall_mae": 0.00006458632,
          "overall_rmse": 0.000072489194,
          "roi_mae": 0.00007679083,
          "roi_rmse": 0.00008592822,
          "non_roi_mae": 0.00006289236,
          "non_roi_rmse": 0.000070421585,
          "roi_mean_spp": 2.0,
          "non_roi_mean_spp": 2.0,
          "max_spp": 2,
          "allocation_concentration": 1.0,
          "extra_roi_samples_vs_uniform": 0.0,
          "roi_error_reduction_per_extra_roi_sample": 0.0
        },
        {
          "policy_id": "contrast_guided",
          "label": "Contrast-guided",
          "total_samples": 30720,
          "overall_mae": 0.00006458632,
          "overall_rmse": 0.000072489194,
          "roi_mae": 0.00007679083,
          "roi_rmse": 0.00008592822,
          "non_roi_mae": 0.00006289236,
          "non_roi_rmse": 0.000070421585,
          "roi_mean_spp": 2.0,
          "non_roi_mean_spp": 2.0,
          "max_spp": 2,
          "allocation_concentration": 1.0,
          "extra_roi_samples_vs_uniform": 0.0,
          "roi_error_reduction_per_extra_roi_sample": 0.0
        },
        {
          "policy_id": "variance_guided",
          "label": "Variance-guided",
          "total_samples": 30720,
          "overall_mae": 0.00006458632,
          "overall_rmse": 0.000072489194,
          "roi_mae": 0.00007679083,
          "roi_rmse": 0.00008592822,
          "non_roi_mae": 0.00006289236,
          "non_roi_rmse": 0.000070421585,
          "roi_mean_spp": 2.0,
          "non_roi_mean_spp": 2.0,
          "max_spp": 2,
          "allocation_concentration": 1.0,
          "extra_roi_samples_vs_uniform": 0.0,
          "roi_error_reduction_per_extra_roi_sample": 0.0
        },
        {
          "policy_id": "combined_heuristic",
          "label": "Combined heuristic",
          "total_samples": 30720,
          "overall_mae": 0.00006458632,
          "overall_rmse": 0.000072489194,
          "roi_mae": 0.00007679083,
          "roi_rmse": 0.00008592822,
          "non_roi_mae": 0.00006289236,
          "non_roi_rmse": 0.000070421585,
          "roi_mean_spp": 2.0,
          "non_roi_mean_spp": 2.0,
          "max_spp": 2,
          "allocation_concentration": 1.0,
          "extra_roi_samples_vs_uniform": 0.0,
          "roi_error_reduction_per_extra_roi_sample": 0.0
        },
        {
          "policy_id": "native_trust",
          "label": "Native trust",
          "total_samples": 30720,
          "overall_mae": 0.00006458632,
          "overall_rmse": 0.000072489194,
          "roi_mae": 0.00007679083,
          "roi_rmse": 0.00008592822,
          "non_roi_mae": 0.00006289236,
          "non_roi_rmse": 0.000070421585,
          "roi_mean_spp": 2.0,
          "non_roi_mean_spp": 2.0,
          "max_spp": 2,
          "allocation_concentration": 1.0,
          "extra_roi_samples_vs_uniform": 0.0,
          "roi_error_reduction_per_extra_roi_sample": 0.0
        },
        {
          "policy_id": "imported_trust",
          "label": "Imported trust",
          "total_samples": 30720,
          "overall_mae": 0.00006458632,
          "overall_rmse": 0.000072489194,
          "roi_mae": 0.00007679083,
          "roi_rmse": 0.00008592822,
          "non_roi_mae": 0.00006289236,
          "non_roi_rmse": 0.000070421585,
          "roi_mean_spp": 2.0,
          "non_roi_mean_spp": 2.0,
          "max_spp": 2,
          "allocation_concentration": 1.0,
          "extra_roi_samples_vs_uniform": 0.0,
          "roi_error_reduction_per_extra_roi_sample": 0.0
        },
        {
          "policy_id": "hybrid_trust_variance",
          "label": "Hybrid trust + variance",
          "total_samples": 30720,
          "overall_mae": 0.00006458632,
          "overall_rmse": 0.000072489194,
          "roi_mae": 0.00007679083,
          "roi_rmse": 0.00008592822,
          "non_roi_mae": 0.00006289236,
          "non_roi_rmse": 0.000070421585,
          "roi_mean_spp": 2.0,
          "non_roi_mean_spp": 2.0,
          "max_spp": 2,
          "allocation_concentration": 1.0,
          "extra_roi_samples_vs_uniform": 0.0,
          "roi_error_reduction_per_extra_roi_sample": 0.0
        }
      ],
      "headline": "Contrast Pulse Stress: imported-trust ROI MAE 0.00008, combined-heuristic ROI MAE 0.00008, uniform ROI MAE 0.00008.",
      "bounded_note": "Neutral case: guidance is not expected to produce a large win, so non-ROI penalties and concentration behavior matter more than raw ROI gain."
    },
    {
      "scenario_id": "stability_holdout",
      "scenario_title": "Stability Holdout",
      "expectation": "NeutralExpected",
      "support_category": "NegativeControl",
      "sampling_taxonomy": "negative control",
      "demo_b_taxonomy": "variance_limited",
      "onset_frame": 0,
      "target_label": "holdout background patch",
      "target_pixels": 1008,
      "policies": [
        {
          "policy_id": "uniform",
          "label": "Uniform",
          "total_samples": 30720,
          "overall_mae": 0.0030603374,
          "overall_rmse": 0.020548234,
          "roi_mae": 0.006724712,
          "roi_rmse": 0.033848055,
          "non_roi_mae": 0.0028029722,
          "non_roi_rmse": 0.019272266,
          "roi_mean_spp": 2.0,
          "non_roi_mean_spp": 2.0,
          "max_spp": 2,
          "allocation_concentration": 1.0,
          "extra_roi_samples_vs_uniform": 0.0,
          "roi_error_reduction_per_extra_roi_sample": 0.0
        },
        {
          "policy_id": "edge_guided",
          "label": "Edge-guided",
          "total_samples": 30720,
          "overall_mae": 0.0020610155,
          "overall_rmse": 0.01202122,
          "roi_mae": 0.003926337,
          "roi_rmse": 0.017610587,
          "non_roi_mae": 0.0019300105,
          "non_roi_rmse": 0.011527403,
          "roi_mean_spp": 2.3194444,
          "non_roi_mean_spp": 1.9775641,
          "max_spp": 12,
          "allocation_concentration": 1.1728795,
          "extra_roi_samples_vs_uniform": 0.31944442,
          "roi_error_reduction_per_extra_roi_sample": 0.00876013
        },
        {
          "policy_id": "residual_guided",
          "label": "Residual-guided",
          "total_samples": 30720,
          "overall_mae": 0.0021782948,
          "overall_rmse": 0.012934501,
          "roi_mae": 0.004360342,
          "roi_rmse": 0.01941639,
          "non_roi_mae": 0.0020250443,
          "non_roi_rmse": 0.012352157,
          "roi_mean_spp": 2.1200397,
          "non_roi_mean_spp": 1.9915692,
          "max_spp": 12,
          "allocation_concentration": 1.0645072,
          "extra_roi_samples_vs_uniform": 0.1200397,
          "roi_error_reduction_per_extra_roi_sample": 0.019696567
        },
        {
          "policy_id": "contrast_guided",
          "label": "Contrast-guided",
          "total_samples": 30720,
          "overall_mae": 0.0019247492,
          "overall_rmse": 0.01070741,
          "roi_mae": 0.0034773657,
          "roi_rmse": 0.014639119,
          "non_roi_mae": 0.0018157056,
          "non_roi_rmse": 0.010375457,
          "roi_mean_spp": 2.5565476,
          "non_roi_mean_spp": 1.9609114,
          "max_spp": 12,
          "allocation_concentration": 1.3037548,
          "extra_roi_samples_vs_uniform": 0.55654764,
          "roi_error_reduction_per_extra_roi_sample": 0.005834804
        },
        {
          "policy_id": "variance_guided",
          "label": "Variance-guided",
          "total_samples": 30720,
          "overall_mae": 0.0028955585,
          "overall_rmse": 0.02125249,
          "roi_mae": 0.0061998744,
          "roi_rmse": 0.032702595,
          "non_roi_mae": 0.0026634815,
          "non_roi_rmse": 0.020205962,
          "roi_mean_spp": 2.1001985,
          "non_roi_mean_spp": 1.9929626,
          "max_spp": 12,
          "allocation_concentration": 1.0538073,
          "extra_roi_samples_vs_uniform": 0.10019851,
          "roi_error_reduction_per_extra_roi_sample": 0.0052379775
        },
        {
          "policy_id": "combined_heuristic",
          "label": "Combined heuristic",
          "total_samples": 30720,
          "overall_mae": 0.0019332225,
          "overall_rmse": 0.010209623,
          "roi_mae": 0.003633517,
          "roi_rmse": 0.014929682,
          "non_roi_mae": 0.001813809,
          "non_roi_rmse": 0.009793018,
          "roi_mean_spp": 2.2559524,
          "non_roi_mean_spp": 1.9820234,
          "max_spp": 12,
          "allocation_concentration": 1.1382067,
          "extra_roi_samples_vs_uniform": 0.25595236,
          "roi_error_reduction_per_extra_roi_sample": 0.012077227
        },
        {
          "policy_id": "native_trust",
          "label": "Native trust",
          "total_samples": 30720,
          "overall_mae": 0.0020295188,
          "overall_rmse": 0.010862451,
          "roi_mae": 0.0041211545,
          "roi_rmse": 0.017468002,
          "non_roi_mae": 0.0018826185,
          "non_roi_rmse": 0.010239625,
          "roi_mean_spp": 2.1567461,
          "non_roi_mean_spp": 1.988991,
          "max_spp": 12,
          "allocation_concentration": 1.0843418,
          "extra_roi_samples_vs_uniform": 0.15674615,
          "roi_error_reduction_per_extra_roi_sample": 0.016610024
        },
        {
          "policy_id": "imported_trust",
          "label": "Imported trust",
          "total_samples": 30720,
          "overall_mae": 0.0030603374,
          "overall_rmse": 0.020548234,
          "roi_mae": 0.006724712,
          "roi_rmse": 0.033848055,
          "non_roi_mae": 0.0028029722,
          "non_roi_rmse": 0.019272266,
          "roi_mean_spp": 2.0,
          "non_roi_mean_spp": 2.0,
          "max_spp": 2,
          "allocation_concentration": 1.0,
          "extra_roi_samples_vs_uniform": 0.0,
          "roi_error_reduction_per_extra_roi_sample": 0.0
        },
        {
          "policy_id": "hybrid_trust_variance",
          "label": "Hybrid trust + variance",
          "total_samples": 30720,
          "overall_mae": 0.0031844317,
          "overall_rmse": 0.022424916,
          "roi_mae": 0.006915572,
          "roi_rmse": 0.035217997,
          "non_roi_mae": 0.0029223792,
          "non_roi_rmse": 0.021238783,
          "roi_mean_spp": 2.0099206,
          "non_roi_mean_spp": 1.9993032,
          "max_spp": 4,
          "allocation_concentration": 1.0053105,
          "extra_roi_samples_vs_uniform": 0.009920597,
          "roi_error_reduction_per_extra_roi_sample": -0.019238774
        }
      ],
      "headline": "Stability Holdout: imported-trust ROI MAE 0.00672, combined-heuristic ROI MAE 0.00363, uniform ROI MAE 0.00672.",
      "bounded_note": "Neutral case: guidance is not expected to produce a large win, so non-ROI penalties and concentration behavior matter more than raw ROI gain."
    }
  ],
  "budget_efficiency_curves": [
    {
      "scenario_id": "thin_reveal",
      "policy_id": "uniform",
      "points": [
        {
          "average_spp": 1.0,
          "roi_mae": 0.17242382
        },
        {
          "average_spp": 2.0,
          "roi_mae": 0.17225969
        },
        {
          "average_spp": 4.0,
          "roi_mae": 0.17205767
        },
        {
          "average_spp": 8.0,
          "roi_mae": 0.09564322
        }
      ]
    },
    {
      "scenario_id": "thin_reveal",
      "policy_id": "combined_heuristic",
      "points": [
        {
          "average_spp": 1.0,
          "roi_mae": 0.17242382
        },
        {
          "average_spp": 2.0,
          "roi_mae": 0.049770057
        },
        {
          "average_spp": 4.0,
          "roi_mae": 0.031843167
        },
        {
          "average_spp": 8.0,
          "roi_mae": 0.031843167
        }
      ]
    },
    {
      "scenario_id": "thin_reveal",
      "policy_id": "native_trust",
      "points": [
        {
          "average_spp": 1.0,
          "roi_mae": 0.17242382
        },
        {
          "average_spp": 2.0,
          "roi_mae": 0.17215072
        },
        {
          "average_spp": 4.0,
          "roi_mae": 0.031843167
        },
        {
          "average_spp": 8.0,
          "roi_mae": 0.031843167
        }
      ]
    },
    {
      "scenario_id": "thin_reveal",
      "policy_id": "imported_trust",
      "points": [
        {
          "average_spp": 1.0,
          "roi_mae": 0.17242382
        },
        {
          "average_spp": 2.0,
          "roi_mae": 0.031843167
        },
        {
          "average_spp": 4.0,
          "roi_mae": 0.031843167
        },
        {
          "average_spp": 8.0,
          "roi_mae": 0.031843167
        }
      ]
    },
    {
      "scenario_id": "thin_reveal",
      "policy_id": "hybrid_trust_variance",
      "points": [
        {
          "average_spp": 1.0,
          "roi_mae": 0.17242382
        },
        {
          "average_spp": 2.0,
          "roi_mae": 0.17199929
        },
        {
          "average_spp": 4.0,
          "roi_mae": 0.031843167
        },
        {
          "average_spp": 8.0,
          "roi_mae": 0.031843167
        }
      ]
    },
    {
      "scenario_id": "fast_pan",
      "policy_id": "uniform",
      "points": [
        {
          "average_spp": 1.0,
          "roi_mae": 0.011595865
        },
        {
          "average_spp": 2.0,
          "roi_mae": 0.008036769
        },
        {
          "average_spp": 4.0,
          "roi_mae": 0.0050362167
        },
        {
          "average_spp": 8.0,
          "roi_mae": 0.0026686476
        }
      ]
    },
    {
      "scenario_id": "fast_pan",
      "policy_id": "combined_heuristic",
      "points": [
        {
          "average_spp": 1.0,
          "roi_mae": 0.011595865
        },
        {
          "average_spp": 2.0,
          "roi_mae": 0.0060267006
        },
        {
          "average_spp": 4.0,
          "roi_mae": 0.0033808688
        },
        {
          "average_spp": 8.0,
          "roi_mae": 0.002373302
        }
      ]
    },
    {
      "scenario_id": "fast_pan",
      "policy_id": "native_trust",
      "points": [
        {
          "average_spp": 1.0,
          "roi_mae": 0.011595865
        },
        {
          "average_spp": 2.0,
          "roi_mae": 0.0062935613
        },
        {
          "average_spp": 4.0,
          "roi_mae": 0.0031878555
        },
        {
          "average_spp": 8.0,
          "roi_mae": 0.0023219592
        }
      ]
    },
    {
      "scenario_id": "fast_pan",
      "policy_id": "imported_trust",
      "points": [
        {
          "average_spp": 1.0,
          "roi_mae": 0.011595865
        },
        {
          "average_spp": 2.0,
          "roi_mae": 0.002196287
        },
        {
          "average_spp": 4.0,
          "roi_mae": 0.002157449
        },
        {
          "average_spp": 8.0,
          "roi_mae": 0.002157449
        }
      ]
    },
    {
      "scenario_id": "fast_pan",
      "policy_id": "hybrid_trust_variance",
      "points": [
        {
          "average_spp": 1.0,
          "roi_mae": 0.011595865
        },
        {
          "average_spp": 2.0,
          "roi_mae": 0.0038108004
        },
        {
          "average_spp": 4.0,
          "roi_mae": 0.0021837198
        },
        {
          "average_spp": 8.0,
          "roi_mae": 0.002157449
        }
      ]
    },
    {
      "scenario_id": "diagonal_reveal",
      "policy_id": "uniform",
      "points": [
        {
          "average_spp": 1.0,
          "roi_mae": 0.026055092
        },
        {
          "average_spp": 2.0,
          "roi_mae": 0.01606533
        },
        {
          "average_spp": 4.0,
          "roi_mae": 0.012427057
        },
        {
          "average_spp": 8.0,
          "roi_mae": 0.005273784
        }
      ]
    },
    {
      "scenario_id": "diagonal_reveal",
      "policy_id": "combined_heuristic",
      "points": [
        {
          "average_spp": 1.0,
          "roi_mae": 0.026055092
        },
        {
          "average_spp": 2.0,
          "roi_mae": 0.012448907
        },
        {
          "average_spp": 4.0,
          "roi_mae": 0.007695814
        },
        {
          "average_spp": 8.0,
          "roi_mae": 0.007695814
        }
      ]
    },
    {
      "scenario_id": "diagonal_reveal",
      "policy_id": "native_trust",
      "points": [
        {
          "average_spp": 1.0,
          "roi_mae": 0.026055092
        },
        {
          "average_spp": 2.0,
          "roi_mae": 0.012427057
        },
        {
          "average_spp": 4.0,
          "roi_mae": 0.0013634512
        },
        {
          "average_spp": 8.0,
          "roi_mae": 0.007695814
        }
      ]
    },
    {
      "scenario_id": "diagonal_reveal",
      "policy_id": "imported_trust",
      "points": [
        {
          "average_spp": 1.0,
          "roi_mae": 0.026055092
        },
        {
          "average_spp": 2.0,
          "roi_mae": 0.007695814
        },
        {
          "average_spp": 4.0,
          "roi_mae": 0.007695814
        },
        {
          "average_spp": 8.0,
          "roi_mae": 0.007695814
        }
      ]
    },
    {
      "scenario_id": "diagonal_reveal",
      "policy_id": "hybrid_trust_variance",
      "points": [
        {
          "average_spp": 1.0,
          "roi_mae": 0.026055092
        },
        {
          "average_spp": 2.0,
          "roi_mae": 0.012448907
        },
        {
          "average_spp": 4.0,
          "roi_mae": 0.007695814
        },
        {
          "average_spp": 8.0,
          "roi_mae": 0.007695814
        }
      ]
    },
    {
      "scenario_id": "reveal_band",
      "policy_id": "uniform",
      "points": [
        {
          "average_spp": 1.0,
          "roi_mae": 0.021830793
        },
        {
          "average_spp": 2.0,
          "roi_mae": 0.014585863
        },
        {
          "average_spp": 4.0,
          "roi_mae": 0.007054069
        },
        {
          "average_spp": 8.0,
          "roi_mae": 0.0036846078
        }
      ]
    },
    {
      "scenario_id": "reveal_band",
      "policy_id": "combined_heuristic",
      "points": [
        {
          "average_spp": 1.0,
          "roi_mae": 0.021830793
        },
        {
          "average_spp": 2.0,
          "roi_mae": 0.009719432
        },
        {
          "average_spp": 4.0,
          "roi_mae": 0.005776847
        },
        {
          "average_spp": 8.0,
          "roi_mae": 0.0037677889
        }
      ]
    },
    {
      "scenario_id": "reveal_band",
      "policy_id": "native_trust",
      "points": [
        {
          "average_spp": 1.0,
          "roi_mae": 0.021830793
        },
        {
          "average_spp": 2.0,
          "roi_mae": 0.00931733
        },
        {
          "average_spp": 4.0,
          "roi_mae": 0.0058414266
        },
        {
          "average_spp": 8.0,
          "roi_mae": 0.0039308085
        }
      ]
    },
    {
      "scenario_id": "reveal_band",
      "policy_id": "imported_trust",
      "points": [
        {
          "average_spp": 1.0,
          "roi_mae": 0.021830793
        },
        {
          "average_spp": 2.0,
          "roi_mae": 0.0034279888
        },
        {
          "average_spp": 4.0,
          "roi_mae": 0.0034279888
        },
        {
          "average_spp": 8.0,
          "roi_mae": 0.0034279888
        }
      ]
    },
    {
      "scenario_id": "reveal_band",
      "policy_id": "hybrid_trust_variance",
      "points": [
        {
          "average_spp": 1.0,
          "roi_mae": 0.021830793
        },
        {
          "average_spp": 2.0,
          "roi_mae": 0.0053313943
        },
        {
          "average_spp": 4.0,
          "roi_mae": 0.0034279888
        },
        {
          "average_spp": 8.0,
          "roi_mae": 0.0034279888
        }
      ]
    },
    {
      "scenario_id": "motion_bias_band",
      "policy_id": "uniform",
      "points": [
        {
          "average_spp": 1.0,
          "roi_mae": 0.044643294
        },
        {
          "average_spp": 2.0,
          "roi_mae": 0.03228638
        },
        {
          "average_spp": 4.0,
          "roi_mae": 0.01788499
        },
        {
          "average_spp": 8.0,
          "roi_mae": 0.008287245
        }
      ]
    },
    {
      "scenario_id": "motion_bias_band",
      "policy_id": "combined_heuristic",
      "points": [
        {
          "average_spp": 1.0,
          "roi_mae": 0.044643294
        },
        {
          "average_spp": 2.0,
          "roi_mae": 0.01715514
        },
        {
          "average_spp": 4.0,
          "roi_mae": 0.010586019
        },
        {
          "average_spp": 8.0,
          "roi_mae": 0.0070346985
        }
      ]
    },
    {
      "scenario_id": "motion_bias_band",
      "policy_id": "native_trust",
      "points": [
        {
          "average_spp": 1.0,
          "roi_mae": 0.044643294
        },
        {
          "average_spp": 2.0,
          "roi_mae": 0.017891984
        },
        {
          "average_spp": 4.0,
          "roi_mae": 0.010419105
        },
        {
          "average_spp": 8.0,
          "roi_mae": 0.0073114736
        }
      ]
    },
    {
      "scenario_id": "motion_bias_band",
      "policy_id": "imported_trust",
      "points": [
        {
          "average_spp": 1.0,
          "roi_mae": 0.044643294
        },
        {
          "average_spp": 2.0,
          "roi_mae": 0.009735676
        },
        {
          "average_spp": 4.0,
          "roi_mae": 0.0069536394
        },
        {
          "average_spp": 8.0,
          "roi_mae": 0.0069536394
        }
      ]
    },
    {
      "scenario_id": "motion_bias_band",
      "policy_id": "hybrid_trust_variance",
      "points": [
        {
          "average_spp": 1.0,
          "roi_mae": 0.044643294
        },
        {
          "average_spp": 2.0,
          "roi_mae": 0.014983777
        },
        {
          "average_spp": 4.0,
          "roi_mae": 0.0071220845
        },
        {
          "average_spp": 8.0,
          "roi_mae": 0.0069536394
        }
      ]
    },
    {
      "scenario_id": "layered_slats",
      "policy_id": "uniform",
      "points": [
        {
          "average_spp": 1.0,
          "roi_mae": 0.027107112
        },
        {
          "average_spp": 2.0,
          "roi_mae": 0.019847455
        },
        {
          "average_spp": 4.0,
          "roi_mae": 0.010498001
        },
        {
          "average_spp": 8.0,
          "roi_mae": 0.00526003
        }
      ]
    },
    {
      "scenario_id": "layered_slats",
      "policy_id": "combined_heuristic",
      "points": [
        {
          "average_spp": 1.0,
          "roi_mae": 0.027107112
        },
        {
          "average_spp": 2.0,
          "roi_mae": 0.008812139
        },
        {
          "average_spp": 4.0,
          "roi_mae": 0.004718381
        },
        {
          "average_spp": 8.0,
          "roi_mae": 0.0038092118
        }
      ]
    },
    {
      "scenario_id": "layered_slats",
      "policy_id": "native_trust",
      "points": [
        {
          "average_spp": 1.0,
          "roi_mae": 0.027107112
        },
        {
          "average_spp": 2.0,
          "roi_mae": 0.010175551
        },
        {
          "average_spp": 4.0,
          "roi_mae": 0.0048602857
        },
        {
          "average_spp": 8.0,
          "roi_mae": 0.003903457
        }
      ]
    },
    {
      "scenario_id": "layered_slats",
      "policy_id": "imported_trust",
      "points": [
        {
          "average_spp": 1.0,
          "roi_mae": 0.027107112
        },
        {
          "average_spp": 2.0,
          "roi_mae": 0.0035278392
        },
        {
          "average_spp": 4.0,
          "roi_mae": 0.0035278392
        },
        {
          "average_spp": 8.0,
          "roi_mae": 0.0035278392
        }
      ]
    },
    {
      "scenario_id": "layered_slats",
      "policy_id": "hybrid_trust_variance",
      "points": [
        {
          "average_spp": 1.0,
          "roi_mae": 0.027107112
        },
        {
          "average_spp": 2.0,
          "roi_mae": 0.007625702
        },
        {
          "average_spp": 4.0,
          "roi_mae": 0.0035278392
        },
        {
          "average_spp": 8.0,
          "roi_mae": 0.0035278392
        }
      ]
    },
    {
      "scenario_id": "noisy_reprojection",
      "policy_id": "uniform",
      "points": [
        {
          "average_spp": 1.0,
          "roi_mae": 0.045915745
        },
        {
          "average_spp": 2.0,
          "roi_mae": 0.03289715
        },
        {
          "average_spp": 4.0,
          "roi_mae": 0.01810506
        },
        {
          "average_spp": 8.0,
          "roi_mae": 0.008787018
        }
      ]
    },
    {
      "scenario_id": "noisy_reprojection",
      "policy_id": "combined_heuristic",
      "points": [
        {
          "average_spp": 1.0,
          "roi_mae": 0.045915745
        },
        {
          "average_spp": 2.0,
          "roi_mae": 0.02066805
        },
        {
          "average_spp": 4.0,
          "roi_mae": 0.013801436
        },
        {
          "average_spp": 8.0,
          "roi_mae": 0.007403635
        }
      ]
    },
    {
      "scenario_id": "noisy_reprojection",
      "policy_id": "native_trust",
      "points": [
        {
          "average_spp": 1.0,
          "roi_mae": 0.045915745
        },
        {
          "average_spp": 2.0,
          "roi_mae": 0.021494558
        },
        {
          "average_spp": 4.0,
          "roi_mae": 0.013324728
        },
        {
          "average_spp": 8.0,
          "roi_mae": 0.007420146
        }
      ]
    },
    {
      "scenario_id": "noisy_reprojection",
      "policy_id": "imported_trust",
      "points": [
        {
          "average_spp": 1.0,
          "roi_mae": 0.045915745
        },
        {
          "average_spp": 2.0,
          "roi_mae": 0.010562399
        },
        {
          "average_spp": 4.0,
          "roi_mae": 0.0070287
        },
        {
          "average_spp": 8.0,
          "roi_mae": 0.00702353
        }
      ]
    },
    {
      "scenario_id": "noisy_reprojection",
      "policy_id": "hybrid_trust_variance",
      "points": [
        {
          "average_spp": 1.0,
          "roi_mae": 0.045915745
        },
        {
          "average_spp": 2.0,
          "roi_mae": 0.01499264
        },
        {
          "average_spp": 4.0,
          "roi_mae": 0.0072596762
        },
        {
          "average_spp": 8.0,
          "roi_mae": 0.00702353
        }
      ]
    },
    {
      "scenario_id": "heuristic_friendly_pan",
      "policy_id": "uniform",
      "points": [
        {
          "average_spp": 1.0,
          "roi_mae": 0.0154890455
        },
        {
          "average_spp": 2.0,
          "roi_mae": 0.0102981515
        },
        {
          "average_spp": 4.0,
          "roi_mae": 0.006617162
        },
        {
          "average_spp": 8.0,
          "roi_mae": 0.002968713
        }
      ]
    },
    {
      "scenario_id": "heuristic_friendly_pan",
      "policy_id": "combined_heuristic",
      "points": [
        {
          "average_spp": 1.0,
          "roi_mae": 0.0154890455
        },
        {
          "average_spp": 2.0,
          "roi_mae": 0.00691609
        },
        {
          "average_spp": 4.0,
          "roi_mae": 0.003944732
        },
        {
          "average_spp": 8.0,
          "roi_mae": 0.0026507778
        }
      ]
    },
    {
      "scenario_id": "heuristic_friendly_pan",
      "policy_id": "native_trust",
      "points": [
        {
          "average_spp": 1.0,
          "roi_mae": 0.0154890455
        },
        {
          "average_spp": 2.0,
          "roi_mae": 0.007112995
        },
        {
          "average_spp": 4.0,
          "roi_mae": 0.003963914
        },
        {
          "average_spp": 8.0,
          "roi_mae": 0.0027448258
        }
      ]
    },
    {
      "scenario_id": "heuristic_friendly_pan",
      "policy_id": "imported_trust",
      "points": [
        {
          "average_spp": 1.0,
          "roi_mae": 0.0154890455
        },
        {
          "average_spp": 2.0,
          "roi_mae": 0.0025213864
        },
        {
          "average_spp": 4.0,
          "roi_mae": 0.0024097362
        },
        {
          "average_spp": 8.0,
          "roi_mae": 0.0024097362
        }
      ]
    },
    {
      "scenario_id": "heuristic_friendly_pan",
      "policy_id": "hybrid_trust_variance",
      "points": [
        {
          "average_spp": 1.0,
          "roi_mae": 0.0154890455
        },
        {
          "average_spp": 2.0,
          "roi_mae": 0.0047482587
        },
        {
          "average_spp": 4.0,
          "roi_mae": 0.0024097362
        },
        {
          "average_spp": 8.0,
          "roi_mae": 0.0024097362
        }
      ]
    },
    {
      "scenario_id": "contrast_pulse",
      "policy_id": "uniform",
      "points": [
        {
          "average_spp": 1.0,
          "roi_mae": 0.0001277599
        },
        {
          "average_spp": 2.0,
          "roi_mae": 0.00007679083
        },
        {
          "average_spp": 4.0,
          "roi_mae": 0.000041422416
        },
        {
          "average_spp": 8.0,
          "roi_mae": 0.000018338735
        }
      ]
    },
    {
      "scenario_id": "contrast_pulse",
      "policy_id": "combined_heuristic",
      "points": [
        {
          "average_spp": 1.0,
          "roi_mae": 0.0001277599
        },
        {
          "average_spp": 2.0,
          "roi_mae": 0.00007679083
        },
        {
          "average_spp": 4.0,
          "roi_mae": 0.000041422416
        },
        {
          "average_spp": 8.0,
          "roi_mae": 0.000018265939
        }
      ]
    },
    {
      "scenario_id": "contrast_pulse",
      "policy_id": "native_trust",
      "points": [
        {
          "average_spp": 1.0,
          "roi_mae": 0.0001277599
        },
        {
          "average_spp": 2.0,
          "roi_mae": 0.00007679083
        },
        {
          "average_spp": 4.0,
          "roi_mae": 0.000041422416
        },
        {
          "average_spp": 8.0,
          "roi_mae": 0.000018331908
        }
      ]
    },
    {
      "scenario_id": "contrast_pulse",
      "policy_id": "imported_trust",
      "points": [
        {
          "average_spp": 1.0,
          "roi_mae": 0.0001277599
        },
        {
          "average_spp": 2.0,
          "roi_mae": 0.00007679083
        },
        {
          "average_spp": 4.0,
          "roi_mae": 0.000041422416
        },
        {
          "average_spp": 8.0,
          "roi_mae": 0.000018338735
        }
      ]
    },
    {
      "scenario_id": "contrast_pulse",
      "policy_id": "hybrid_trust_variance",
      "points": [
        {
          "average_spp": 1.0,
          "roi_mae": 0.0001277599
        },
        {
          "average_spp": 2.0,
          "roi_mae": 0.00007679083
        },
        {
          "average_spp": 4.0,
          "roi_mae": 0.000041422416
        },
        {
          "average_spp": 8.0,
          "roi_mae": 0.000018338735
        }
      ]
    },
    {
      "scenario_id": "stability_holdout",
      "policy_id": "uniform",
      "points": [
        {
          "average_spp": 1.0,
          "roi_mae": 0.010073278
        },
        {
          "average_spp": 2.0,
          "roi_mae": 0.006724712
        },
        {
          "average_spp": 4.0,
          "roi_mae": 0.004727598
        },
        {
          "average_spp": 8.0,
          "roi_mae": 0.002742794
        }
      ]
    },
    {
      "scenario_id": "stability_holdout",
      "policy_id": "combined_heuristic",
      "points": [
        {
          "average_spp": 1.0,
          "roi_mae": 0.010073278
        },
        {
          "average_spp": 2.0,
          "roi_mae": 0.003633517
        },
        {
          "average_spp": 4.0,
          "roi_mae": 0.0026832737
        },
        {
          "average_spp": 8.0,
          "roi_mae": 0.0021596083
        }
      ]
    },
    {
      "scenario_id": "stability_holdout",
      "policy_id": "native_trust",
      "points": [
        {
          "average_spp": 1.0,
          "roi_mae": 0.010073278
        },
        {
          "average_spp": 2.0,
          "roi_mae": 0.0041211545
        },
        {
          "average_spp": 4.0,
          "roi_mae": 0.0026398548
        },
        {
          "average_spp": 8.0,
          "roi_mae": 0.0021509682
        }
      ]
    },
    {
      "scenario_id": "stability_holdout",
      "policy_id": "imported_trust",
      "points": [
        {
          "average_spp": 1.0,
          "roi_mae": 0.010073278
        },
        {
          "average_spp": 2.0,
          "roi_mae": 0.006724712
        },
        {
          "average_spp": 4.0,
          "roi_mae": 0.004727598
        },
        {
          "average_spp": 8.0,
          "roi_mae": 0.002742794
        }
      ]
    },
    {
      "scenario_id": "stability_holdout",
      "policy_id": "hybrid_trust_variance",
      "points": [
        {
          "average_spp": 1.0,
          "roi_mae": 0.010073278
        },
        {
          "average_spp": 2.0,
          "roi_mae": 0.006915572
        },
        {
          "average_spp": 4.0,
          "roi_mae": 0.004062821
        },
        {
          "average_spp": 8.0,
          "roi_mae": 0.0026637048
        }
      ]
    }
  ]
}